wyse/_vendor/pip/_internal/operations/build/__init__.py
wyse/_vendor/pip/_internal/operations/build/build_tracker.py
wyse/_vendor/pip/_internal/operations/build/metadata.py
wyse/_vendor/pip/_internal/operations/build/metadata_editable.py
wyse/_vendor/pip/_internal/operations/build/metadata_legacy.py
wyse/_vendor/pip/_internal/operations/build/wheel.py
wyse/_vendor/pip/_internal/operations/build/wheel_editable.py
wyse/_vendor/pip/_internal/operations/build/wheel_legacy.py
wyse-0.0.0.dist-info/METADATA
wyse-0.0.0.dist-info/WHEEL
wyse-0.0.0.dist-info/entry_points.txt
wyse-0.0.0.dist-info/top_level.txt
wyse-0.0.0.dist-info/RECORD
