Metadata-Version: 2.1
Name: wyse
Version: 0.0.0
Summary: Coming soon...
Classifier: Development Status :: 3 - Alpha
Requires-Python: >=3.10
